{
  "openapi": "3.0.0",
  "info": {},
  "paths": {
    "/auth/login": {
      "post": {
        "x-controller-name": "LoginController",
        "x-operation-name": "login",
        "tags": [
          "LoginController"
        ],
        "responses": {
          "200": {
            "description": "Auth Code",
            "content": {}
          }
        },
        "requestBody": {
          "content": {
            "application/json": {
              "schema": {
                "$ref": "#/components/schemas/LoginRequest"
              }
            }
          }
        },
        "operationId": "LoginController.login"
      }
    },
    "/auth/token": {
      "post": {
        "x-controller-name": "LoginController",
        "x-operation-name": "token",
        "tags": [
          "LoginController"
        ],
        "responses": {
          "200": {
            "description": "Return value of LoginController.token"
          }
        },
        "requestBody": {
          "content": {
            "application/json": {
              "schema": {
                "$ref": "#/components/schemas/AuthTokenRequest"
              }
            }
          }
        },
        "operationId": "LoginController.token"
      }
    },
    "/auth/token-refresh": {
      "post": {
        "x-controller-name": "LoginController",
        "x-operation-name": "exchangeToken",
        "tags": [
          "LoginController"
        ],
        "responses": {
          "200": {
            "description": "Token Response",
            "content": {
              "application/json": {
                "schema": {
                  "$ref": "#/components/schemas/TokenResponse"
                }
              }
            }
          }
        },
        "requestBody": {
          "content": {
            "application/json": {
              "schema": {
                "$ref": "#/components/schemas/AuthRefreshTokenRequest"
              }
            }
          }
        },
        "operationId": "LoginController.exchangeToken"
      }
    },
    "/logout": {
      "post": {
        "x-controller-name": "LogoutController",
        "x-operation-name": "logout",
        "tags": [
          "LogoutController"
        ],
        "responses": {
          "200": {
            "description": "logout success"
          }
        },
        "security": [
          {
            "token": []
          }
        ],
        "parameters": [
          {
            "name": "Authorization",
            "in": "header",
            "schema": {
              "type": "string"
            }
          }
        ],
        "operationId": "LogoutController.logout"
      }
    },
    "/ping/deny-all": {
      "get": {
        "x-controller-name": "PingController",
        "x-operation-name": "testDenyAll",
        "tags": [
          "PingController"
        ],
        "responses": {
          "200": {
            "description": "ping success"
          }
        },
        "security": [
          {
            "token": []
          }
        ],
        "operationId": "PingController.testDenyAll"
      }
    },
    "/ping/has-any-role": {
      "get": {
        "x-controller-name": "PingController",
        "x-operation-name": "testHasAnyRole",
        "tags": [
          "PingController"
        ],
        "responses": {
          "200": {
            "description": "ping success"
          }
        },
        "security": [
          {
            "token": []
          }
        ],
        "operationId": "PingController.testHasAnyRole"
      }
    },
    "/ping/has-roles": {
      "get": {
        "x-controller-name": "PingController",
        "x-operation-name": "testHasRoles",
        "tags": [
          "PingController"
        ],
        "responses": {
          "200": {
            "description": "ping success"
          }
        },
        "security": [
          {
            "token": []
          }
        ],
        "operationId": "PingController.testHasRoles"
      }
    },
    "/ping/is-authenticated": {
      "get": {
        "x-controller-name": "PingController",
        "x-operation-name": "testIsAuthenticated",
        "tags": [
          "PingController"
        ],
        "responses": {
          "200": {
            "description": "ping success"
          }
        },
        "security": [
          {
            "token": []
          }
        ],
        "operationId": "PingController.testIsAuthenticated"
      }
    },
    "/ping/permit-all": {
      "get": {
        "x-controller-name": "PingController",
        "x-operation-name": "testPermitAll",
        "tags": [
          "PingController"
        ],
        "responses": {
          "200": {
            "description": "ping success"
          }
        },
        "security": [
          {
            "token": []
          }
        ],
        "operationId": "PingController.testPermitAll"
      }
    },
    "/ping": {
      "get": {
        "x-controller-name": "PingController",
        "x-operation-name": "ping",
        "tags": [
          "PingController"
        ],
        "responses": {
          "200": {
            "description": "Ping Response",
            "content": {
              "application/json": {
                "schema": {
                  "type": "object",
                  "properties": {
                    "greeting": {
                      "type": "string"
                    },
                    "date": {
                      "type": "string"
                    },
                    "url": {
                      "type": "string"
                    },
                    "headers": {
                      "type": "object",
                      "properties": {
                        "Content-Type": {
                          "type": "string"
                        }
                      },
                      "additionalProperties": true
                    }
                  }
                }
              }
            }
          }
        },
        "operationId": "PingController.ping"
      }
    },
    "/roles/count": {
      "get": {
        "x-controller-name": "RoleController",
        "x-operation-name": "count",
        "tags": [
          "RoleController"
        ],
        "responses": {
          "200": {
            "description": "Role model count",
            "content": {
              "application/json": {
                "schema": {
                  "type": "object",
                  "title": "loopback.Count",
                  "properties": {
                    "count": {
                      "type": "number"
                    }
                  }
                }
              }
            }
          }
        },
        "security": [
          {
            "token": []
          }
        ],
        "parameters": [
          {
            "name": "where",
            "in": "query",
            "content": {
              "application/json": {
                "schema": {
                  "type": "object",
                  "title": "Role.WhereFilter",
                  "additionalProperties": true
                }
              }
            }
          }
        ],
        "operationId": "RoleController.count"
      }
    },
    "/roles/{id}": {
      "put": {
        "x-controller-name": "RoleController",
        "x-operation-name": "replaceById",
        "tags": [
          "RoleController"
        ],
        "responses": {
          "204": {
            "description": "Role PUT success"
          }
        },
        "security": [
          {
            "token": []
          }
        ],
        "parameters": [
          {
            "name": "id",
            "in": "path",
            "schema": {
              "type": "string"
            },
            "required": true
          }
        ],
        "requestBody": {
          "content": {
            "application/json": {
              "schema": {
                "$ref": "#/components/schemas/Role"
              }
            }
          },
          "x-parameter-index": 1
        },
        "operationId": "RoleController.replaceById"
      },
      "patch": {
        "x-controller-name": "RoleController",
        "x-operation-name": "updateById",
        "tags": [
          "RoleController"
        ],
        "responses": {
          "204": {
            "description": "Role PATCH success"
          }
        },
        "security": [
          {
            "token": []
          }
        ],
        "parameters": [
          {
            "name": "id",
            "in": "path",
            "schema": {
              "type": "string"
            },
            "required": true
          }
        ],
        "requestBody": {
          "content": {
            "application/json": {
              "schema": {
                "$ref": "#/components/schemas/RolePartial"
              }
            }
          },
          "x-parameter-index": 1
        },
        "operationId": "RoleController.updateById"
      },
      "get": {
        "x-controller-name": "RoleController",
        "x-operation-name": "findById",
        "tags": [
          "RoleController"
        ],
        "responses": {
          "200": {
            "description": "Role model instance",
            "content": {
              "application/json": {
                "schema": {
                  "$ref": "#/components/schemas/Role"
                }
              }
            }
          }
        },
        "security": [
          {
            "token": []
          }
        ],
        "parameters": [
          {
            "name": "id",
            "in": "path",
            "schema": {
              "type": "string"
            },
            "required": true
          }
        ],
        "operationId": "RoleController.findById"
      },
      "delete": {
        "x-controller-name": "RoleController",
        "x-operation-name": "deleteById",
        "tags": [
          "RoleController"
        ],
        "responses": {
          "204": {
            "description": "Role DELETE success"
          }
        },
        "security": [
          {
            "token": []
          }
        ],
        "parameters": [
          {
            "name": "id",
            "in": "path",
            "schema": {
              "type": "string"
            },
            "required": true
          }
        ],
        "operationId": "RoleController.deleteById"
      }
    },
    "/roles": {
      "post": {
        "x-controller-name": "RoleController",
        "x-operation-name": "create",
        "tags": [
          "RoleController"
        ],
        "responses": {
          "200": {
            "description": "Role model instance",
            "content": {
              "application/json": {
                "schema": {
                  "$ref": "#/components/schemas/Role"
                }
              }
            }
          }
        },
        "security": [
          {
            "token": []
          }
        ],
        "requestBody": {
          "content": {
            "application/json": {
              "schema": {
                "$ref": "#/components/schemas/RoleExcluding_id_"
              }
            }
          }
        },
        "operationId": "RoleController.create"
      },
      "patch": {
        "x-controller-name": "RoleController",
        "x-operation-name": "updateAll",
        "tags": [
          "RoleController"
        ],
        "responses": {
          "200": {
            "description": "Role PATCH success count",
            "content": {
              "application/json": {
                "schema": {
                  "type": "object",
                  "title": "loopback.Count",
                  "properties": {
                    "count": {
                      "type": "number"
                    }
                  }
                }
              }
            }
          }
        },
        "security": [
          {
            "token": []
          }
        ],
        "parameters": [
          {
            "name": "where",
            "in": "query",
            "content": {
              "application/json": {
                "schema": {
                  "type": "object",
                  "title": "Role.WhereFilter",
                  "additionalProperties": true
                }
              }
            }
          }
        ],
        "requestBody": {
          "content": {
            "application/json": {
              "schema": {
                "$ref": "#/components/schemas/RolePartial"
              }
            }
          }
        },
        "operationId": "RoleController.updateAll"
      },
      "get": {
        "x-controller-name": "RoleController",
        "x-operation-name": "find",
        "tags": [
          "RoleController"
        ],
        "responses": {
          "200": {
            "description": "Array of Role model instances",
            "content": {
              "application/json": {
                "schema": {
                  "type": "array",
                  "items": {
                    "$ref": "#/components/schemas/Role"
                  }
                }
              }
            }
          }
        },
        "security": [
          {
            "token": []
          }
        ],
        "parameters": [
          {
            "name": "filter",
            "in": "query",
            "content": {
              "application/json": {
                "schema": {
                  "type": "object",
                  "title": "Role.Filter",
                  "properties": {
                    "offset": {
                      "type": "integer",
                      "minimum": 0
                    },
                    "limit": {
                      "type": "integer",
                      "minimum": 1,
                      "example": 100
                    },
                    "skip": {
                      "type": "integer",
                      "minimum": 0
                    },
                    "order": {
                      "type": "array",
                      "items": {
                        "type": "string"
                      }
                    },
                    "where": {
                      "title": "Role.WhereFilter",
                      "type": "object",
                      "additionalProperties": true
                    },
                    "fields": {
                      "title": "Role.Fields",
                      "type": "object",
                      "properties": {
                        "deleted": {
                          "type": "boolean"
                        },
                        "createdOn": {
                          "type": "boolean"
                        },
                        "modifiedOn": {
                          "type": "boolean"
                        },
                        "id": {
                          "type": "boolean"
                        },
                        "description": {
                          "type": "boolean"
                        },
                        "name": {
                          "type": "boolean"
                        },
                        "nameWeb": {
                          "type": "boolean"
                        }
                      },
                      "additionalProperties": true
                    }
                  },
                  "additionalProperties": false
                }
              }
            }
          }
        ],
        "operationId": "RoleController.find"
      }
    },
    "/user-roles/count": {
      "get": {
        "x-controller-name": "UserRoleController",
        "x-operation-name": "count",
        "tags": [
          "UserRoleController"
        ],
        "responses": {
          "200": {
            "description": "UserRole model count",
            "content": {
              "application/json": {
                "schema": {
                  "type": "object",
                  "title": "loopback.Count",
                  "properties": {
                    "count": {
                      "type": "number"
                    }
                  }
                }
              }
            }
          }
        },
        "security": [
          {
            "token": []
          }
        ],
        "parameters": [
          {
            "name": "where",
            "in": "query",
            "content": {
              "application/json": {
                "schema": {
                  "type": "object",
                  "title": "UserRole.WhereFilter",
                  "additionalProperties": true
                }
              }
            }
          }
        ],
        "operationId": "UserRoleController.count"
      }
    },
    "/user-roles/{id}": {
      "put": {
        "x-controller-name": "UserRoleController",
        "x-operation-name": "replaceById",
        "tags": [
          "UserRoleController"
        ],
        "responses": {
          "204": {
            "description": "UserRole PUT success"
          }
        },
        "security": [
          {
            "token": []
          }
        ],
        "parameters": [
          {
            "name": "id",
            "in": "path",
            "schema": {
              "type": "string"
            },
            "required": true
          }
        ],
        "requestBody": {
          "content": {
            "application/json": {
              "schema": {
                "$ref": "#/components/schemas/UserRole"
              }
            }
          },
          "x-parameter-index": 1
        },
        "operationId": "UserRoleController.replaceById"
      },
      "patch": {
        "x-controller-name": "UserRoleController",
        "x-operation-name": "updateById",
        "tags": [
          "UserRoleController"
        ],
        "responses": {
          "204": {
            "description": "UserRole PATCH success"
          }
        },
        "security": [
          {
            "token": []
          }
        ],
        "parameters": [
          {
            "name": "id",
            "in": "path",
            "schema": {
              "type": "string"
            },
            "required": true
          }
        ],
        "requestBody": {
          "content": {
            "application/json": {
              "schema": {
                "$ref": "#/components/schemas/UserRolePartial"
              }
            }
          },
          "x-parameter-index": 1
        },
        "operationId": "UserRoleController.updateById"
      },
      "get": {
        "x-controller-name": "UserRoleController",
        "x-operation-name": "findById",
        "tags": [
          "UserRoleController"
        ],
        "responses": {
          "200": {
            "description": "UserRole model instance",
            "content": {
              "application/json": {
                "schema": {
                  "$ref": "#/components/schemas/UserRole"
                }
              }
            }
          }
        },
        "security": [
          {
            "token": []
          }
        ],
        "parameters": [
          {
            "name": "id",
            "in": "path",
            "schema": {
              "type": "string"
            },
            "required": true
          }
        ],
        "operationId": "UserRoleController.findById"
      },
      "delete": {
        "x-controller-name": "UserRoleController",
        "x-operation-name": "deleteById",
        "tags": [
          "UserRoleController"
        ],
        "responses": {
          "204": {
            "description": "UserRole DELETE success"
          }
        },
        "security": [
          {
            "token": []
          }
        ],
        "parameters": [
          {
            "name": "id",
            "in": "path",
            "schema": {
              "type": "string"
            },
            "required": true
          }
        ],
        "operationId": "UserRoleController.deleteById"
      }
    },
    "/user-roles": {
      "post": {
        "x-controller-name": "UserRoleController",
        "x-operation-name": "create",
        "tags": [
          "UserRoleController"
        ],
        "responses": {
          "200": {
            "description": "UserRole model instance",
            "content": {
              "application/json": {
                "schema": {
                  "$ref": "#/components/schemas/UserRole"
                }
              }
            }
          }
        },
        "security": [
          {
            "token": []
          }
        ],
        "requestBody": {
          "content": {
            "application/json": {
              "schema": {
                "$ref": "#/components/schemas/UserRoleExcluding_id_"
              }
            }
          }
        },
        "operationId": "UserRoleController.create"
      },
      "patch": {
        "x-controller-name": "UserRoleController",
        "x-operation-name": "updateAll",
        "tags": [
          "UserRoleController"
        ],
        "responses": {
          "200": {
            "description": "UserRole PATCH success count",
            "content": {
              "application/json": {
                "schema": {
                  "type": "object",
                  "title": "loopback.Count",
                  "properties": {
                    "count": {
                      "type": "number"
                    }
                  }
                }
              }
            }
          }
        },
        "security": [
          {
            "token": []
          }
        ],
        "parameters": [
          {
            "name": "where",
            "in": "query",
            "content": {
              "application/json": {
                "schema": {
                  "type": "object",
                  "title": "UserRole.WhereFilter",
                  "additionalProperties": true
                }
              }
            }
          }
        ],
        "requestBody": {
          "content": {
            "application/json": {
              "schema": {
                "$ref": "#/components/schemas/UserRolePartial"
              }
            }
          }
        },
        "operationId": "UserRoleController.updateAll"
      },
      "get": {
        "x-controller-name": "UserRoleController",
        "x-operation-name": "find",
        "tags": [
          "UserRoleController"
        ],
        "responses": {
          "200": {
            "description": "Array of UserRole model instances",
            "content": {
              "application/json": {
                "schema": {
                  "type": "array",
                  "items": {
                    "$ref": "#/components/schemas/UserRole"
                  }
                }
              }
            }
          }
        },
        "security": [
          {
            "token": []
          }
        ],
        "parameters": [
          {
            "name": "filter",
            "in": "query",
            "content": {
              "application/json": {
                "schema": {
                  "type": "object",
                  "title": "UserRole.Filter",
                  "properties": {
                    "offset": {
                      "type": "integer",
                      "minimum": 0
                    },
                    "limit": {
                      "type": "integer",
                      "minimum": 1,
                      "example": 100
                    },
                    "skip": {
                      "type": "integer",
                      "minimum": 0
                    },
                    "order": {
                      "type": "array",
                      "items": {
                        "type": "string"
                      }
                    },
                    "where": {
                      "title": "UserRole.WhereFilter",
                      "type": "object",
                      "additionalProperties": true
                    },
                    "fields": {
                      "title": "UserRole.Fields",
                      "type": "object",
                      "properties": {
                        "deleted": {
                          "type": "boolean"
                        },
                        "createdOn": {
                          "type": "boolean"
                        },
                        "modifiedOn": {
                          "type": "boolean"
                        },
                        "id": {
                          "type": "boolean"
                        },
                        "userId": {
                          "type": "boolean"
                        },
                        "roleId": {
                          "type": "boolean"
                        }
                      },
                      "additionalProperties": true
                    },
                    "include": {
                      "title": "UserRole.IncludeFilter",
                      "type": "array",
                      "items": {
                        "title": "UserRole.IncludeFilter.Items",
                        "type": "object",
                        "properties": {
                          "relation": {
                            "type": "string"
                          },
                          "scope": {
                            "properties": {
                              "offset": {
                                "type": "integer",
                                "minimum": 0
                              },
                              "limit": {
                                "type": "integer",
                                "minimum": 1,
                                "example": 100
                              },
                              "skip": {
                                "type": "integer",
                                "minimum": 0
                              },
                              "order": {
                                "type": "array",
                                "items": {
                                  "type": "string"
                                }
                              },
                              "where": {
                                "type": "object",
                                "additionalProperties": true
                              },
                              "fields": {
                                "type": "object",
                                "properties": {},
                                "additionalProperties": true
                              }
                            },
                            "additionalProperties": false,
                            "title": "UserRole.ScopeFilter"
                          }
                        }
                      }
                    }
                  },
                  "additionalProperties": false
                }
              }
            }
          }
        ],
        "operationId": "UserRoleController.find"
      }
    },
    "/users/count": {
      "get": {
        "x-controller-name": "UserController",
        "x-operation-name": "count",
        "tags": [
          "UserController"
        ],
        "responses": {
          "200": {
            "description": "User model count",
            "content": {
              "application/json": {
                "schema": {
                  "type": "object",
                  "title": "loopback.Count",
                  "properties": {
                    "count": {
                      "type": "number"
                    }
                  }
                }
              }
            }
          }
        },
        "security": [
          {
            "token": []
          }
        ],
        "parameters": [
          {
            "name": "where",
            "in": "query",
            "content": {
              "application/json": {
                "schema": {
                  "type": "object",
                  "title": "User.WhereFilter",
                  "additionalProperties": true
                }
              }
            }
          }
        ],
        "operationId": "UserController.count"
      }
    },
    "/users/{id}": {
      "put": {
        "x-controller-name": "UserController",
        "x-operation-name": "replaceById",
        "tags": [
          "UserController"
        ],
        "responses": {
          "204": {
            "description": "User PUT success"
          }
        },
        "security": [
          {
            "token": []
          }
        ],
        "parameters": [
          {
            "name": "id",
            "in": "path",
            "schema": {
              "type": "string"
            },
            "required": true
          }
        ],
        "requestBody": {
          "content": {
            "application/json": {
              "schema": {
                "$ref": "#/components/schemas/User"
              }
            }
          },
          "x-parameter-index": 1
        },
        "operationId": "UserController.replaceById"
      },
      "patch": {
        "x-controller-name": "UserController",
        "x-operation-name": "updateById",
        "tags": [
          "UserController"
        ],
        "responses": {
          "204": {
            "description": "User PATCH success"
          }
        },
        "security": [
          {
            "token": []
          }
        ],
        "parameters": [
          {
            "name": "id",
            "in": "path",
            "schema": {
              "type": "string"
            },
            "required": true
          }
        ],
        "requestBody": {
          "content": {
            "application/json": {
              "schema": {
                "$ref": "#/components/schemas/UserPartial"
              }
            }
          },
          "x-parameter-index": 1
        },
        "operationId": "UserController.updateById"
      },
      "get": {
        "x-controller-name": "UserController",
        "x-operation-name": "findById",
        "tags": [
          "UserController"
        ],
        "responses": {
          "200": {
            "description": "User model instance",
            "content": {
              "application/json": {
                "schema": {
                  "$ref": "#/components/schemas/User"
                }
              }
            }
          }
        },
        "security": [
          {
            "token": []
          }
        ],
        "parameters": [
          {
            "name": "id",
            "in": "path",
            "schema": {
              "type": "string"
            },
            "required": true
          }
        ],
        "operationId": "UserController.findById"
      },
      "delete": {
        "x-controller-name": "UserController",
        "x-operation-name": "deleteById",
        "tags": [
          "UserController"
        ],
        "responses": {
          "204": {
            "description": "User DELETE success"
          }
        },
        "security": [
          {
            "token": []
          }
        ],
        "parameters": [
          {
            "name": "id",
            "in": "path",
            "schema": {
              "type": "string"
            },
            "required": true
          }
        ],
        "operationId": "UserController.deleteById"
      }
    },
    "/users": {
      "post": {
        "x-controller-name": "UserController",
        "x-operation-name": "create",
        "tags": [
          "UserController"
        ],
        "responses": {
          "200": {
            "description": "User model instance",
            "content": {
              "application/json": {
                "schema": {
                  "$ref": "#/components/schemas/User"
                }
              }
            }
          }
        },
        "security": [
          {
            "token": []
          }
        ],
        "requestBody": {
          "content": {
            "application/json": {
              "schema": {
                "$ref": "#/components/schemas/UserExcluding_id_"
              }
            }
          }
        },
        "operationId": "UserController.create"
      },
      "patch": {
        "x-controller-name": "UserController",
        "x-operation-name": "updateAll",
        "tags": [
          "UserController"
        ],
        "responses": {
          "200": {
            "description": "User PATCH success count",
            "content": {
              "application/json": {
                "schema": {
                  "type": "object",
                  "title": "loopback.Count",
                  "properties": {
                    "count": {
                      "type": "number"
                    }
                  }
                }
              }
            }
          }
        },
        "security": [
          {
            "token": []
          }
        ],
        "parameters": [
          {
            "name": "where",
            "in": "query",
            "content": {
              "application/json": {
                "schema": {
                  "type": "object",
                  "title": "User.WhereFilter",
                  "additionalProperties": true
                }
              }
            }
          }
        ],
        "requestBody": {
          "content": {
            "application/json": {
              "schema": {
                "$ref": "#/components/schemas/UserPartial"
              }
            }
          }
        },
        "operationId": "UserController.updateAll"
      },
      "get": {
        "x-controller-name": "UserController",
        "x-operation-name": "find",
        "tags": [
          "UserController"
        ],
        "responses": {
          "200": {
            "description": "Array of User model instances",
            "content": {
              "application/json": {
                "schema": {
                  "type": "array",
                  "items": {
                    "$ref": "#/components/schemas/User"
                  }
                }
              }
            }
          }
        },
        "security": [
          {
            "token": []
          }
        ],
        "parameters": [
          {
            "name": "filter",
            "in": "query",
            "content": {
              "application/json": {
                "schema": {
                  "type": "object",
                  "title": "User.Filter",
                  "properties": {
                    "offset": {
                      "type": "integer",
                      "minimum": 0
                    },
                    "limit": {
                      "type": "integer",
                      "minimum": 1,
                      "example": 100
                    },
                    "skip": {
                      "type": "integer",
                      "minimum": 0
                    },
                    "order": {
                      "type": "array",
                      "items": {
                        "type": "string"
                      }
                    },
                    "where": {
                      "title": "User.WhereFilter",
                      "type": "object",
                      "additionalProperties": true
                    },
                    "fields": {
                      "title": "User.Fields",
                      "type": "object",
                      "properties": {
                        "deleted": {
                          "type": "boolean"
                        },
                        "createdOn": {
                          "type": "boolean"
                        },
                        "modifiedOn": {
                          "type": "boolean"
                        },
                        "createdBy": {
                          "type": "boolean"
                        },
                        "modifiedBy": {
                          "type": "boolean"
                        },
                        "id": {
                          "type": "boolean"
                        },
                        "email": {
                          "type": "boolean"
                        },
                        "firstName": {
                          "type": "boolean"
                        },
                        "lastName": {
                          "type": "boolean"
                        },
                        "lastLogin": {
                          "type": "boolean"
                        },
                        "username": {
                          "type": "boolean"
                        },
                        "password": {
                          "type": "boolean"
                        }
                      },
                      "additionalProperties": true
                    },
                    "include": {
                      "title": "User.IncludeFilter",
                      "type": "array",
                      "items": {
                        "title": "User.IncludeFilter.Items",
                        "type": "object",
                        "properties": {
                          "relation": {
                            "type": "string"
                          },
                          "scope": {
                            "properties": {
                              "offset": {
                                "type": "integer",
                                "minimum": 0
                              },
                              "limit": {
                                "type": "integer",
                                "minimum": 1,
                                "example": 100
                              },
                              "skip": {
                                "type": "integer",
                                "minimum": 0
                              },
                              "order": {
                                "type": "array",
                                "items": {
                                  "type": "string"
                                }
                              },
                              "where": {
                                "type": "object",
                                "additionalProperties": true
                              },
                              "fields": {
                                "type": "object",
                                "properties": {},
                                "additionalProperties": true
                              }
                            },
                            "additionalProperties": false,
                            "title": "User.ScopeFilter"
                          }
                        }
                      }
                    }
                  },
                  "additionalProperties": false
                }
              }
            }
          }
        ],
        "operationId": "UserController.find"
      }
    },
    "/whoami": {
      "get": {
        "x-controller-name": "WhoamiController",
        "x-operation-name": "whoami",
        "tags": [
          "WhoamiController"
        ],
        "responses": {
          "200": {
            "description": "PGP keys",
            "content": {
              "application/json": {
                "schema": {
                  "$ref": "#/components/schemas/PGP"
                }
              }
            }
          }
        },
        "operationId": "WhoamiController.whoami"
      }
    }
  },
  "components": {
    "securitySchemes": {
      "token": {
        "type": "http",
        "scheme": "bearer",
        "bearerFormat": "JWT",
        "in": "header"
      }
    },
    "schemas": {
      "Role": {
        "title": "Role",
        "properties": {
          "deleted": {
            "type": "boolean"
          },
          "createdOn": {
            "type": "string",
            "format": "date-time"
          },
          "modifiedOn": {
            "type": "string",
            "format": "date-time"
          },
          "id": {
            "type": "string"
          },
          "description": {
            "type": "string"
          },
          "name": {
            "type": "string"
          },
          "nameWeb": {
            "type": "string"
          }
        },
        "required": [
          "name"
        ],
        "additionalProperties": true
      },
      "RoleExcluding_id_": {
        "title": "RoleExcluding_id_",
        "description": "(Schema options: { exclude: [ 'id' ] })",
        "properties": {
          "deleted": {
            "type": "boolean"
          },
          "createdOn": {
            "type": "string",
            "format": "date-time"
          },
          "modifiedOn": {
            "type": "string",
            "format": "date-time"
          },
          "description": {
            "type": "string"
          },
          "name": {
            "type": "string"
          },
          "nameWeb": {
            "type": "string"
          }
        },
        "required": [
          "name"
        ],
        "additionalProperties": true
      },
      "RolePartial": {
        "title": "RolePartial",
        "description": "(Schema options: { partial: true })",
        "properties": {
          "deleted": {
            "type": "boolean"
          },
          "createdOn": {
            "type": "string",
            "format": "date-time"
          },
          "modifiedOn": {
            "type": "string",
            "format": "date-time"
          },
          "id": {
            "type": "string"
          },
          "description": {
            "type": "string"
          },
          "name": {
            "type": "string"
          },
          "nameWeb": {
            "type": "string"
          }
        },
        "additionalProperties": true
      },
      "UserRole": {
        "title": "UserRole",
        "properties": {
          "deleted": {
            "type": "boolean"
          },
          "createdOn": {
            "type": "string",
            "format": "date-time"
          },
          "modifiedOn": {
            "type": "string",
            "format": "date-time"
          },
          "id": {
            "type": "string"
          },
          "userId": {
            "type": "string"
          },
          "roleId": {
            "type": "string"
          }
        },
        "additionalProperties": true
      },
      "UserRoleExcluding_id_": {
        "title": "UserRoleExcluding_id_",
        "description": "(Schema options: { exclude: [ 'id' ] })",
        "properties": {
          "deleted": {
            "type": "boolean"
          },
          "createdOn": {
            "type": "string",
            "format": "date-time"
          },
          "modifiedOn": {
            "type": "string",
            "format": "date-time"
          },
          "userId": {
            "type": "string"
          },
          "roleId": {
            "type": "string"
          }
        },
        "additionalProperties": true
      },
      "UserRolePartial": {
        "title": "UserRolePartial",
        "description": "(Schema options: { partial: true })",
        "properties": {
          "deleted": {
            "type": "boolean"
          },
          "createdOn": {
            "type": "string",
            "format": "date-time"
          },
          "modifiedOn": {
            "type": "string",
            "format": "date-time"
          },
          "id": {
            "type": "string"
          },
          "userId": {
            "type": "string"
          },
          "roleId": {
            "type": "string"
          }
        },
        "additionalProperties": true
      },
      "User": {
        "title": "User",
        "properties": {
          "deleted": {
            "type": "boolean"
          },
          "createdOn": {
            "type": "string",
            "format": "date-time"
          },
          "modifiedOn": {
            "type": "string",
            "format": "date-time"
          },
          "createdBy": {
            "type": "string"
          },
          "modifiedBy": {
            "type": "string"
          },
          "id": {
            "type": "string"
          },
          "email": {
            "type": "string"
          },
          "firstName": {
            "type": "string"
          },
          "lastName": {
            "type": "string"
          },
          "lastLogin": {
            "type": "string",
            "format": "date-time"
          },
          "username": {
            "type": "string"
          },
          "password": {
            "type": "string"
          }
        },
        "required": [
          "email",
          "firstName",
          "lastName",
          "username"
        ],
        "additionalProperties": true
      },
      "UserExcluding_id_": {
        "title": "UserExcluding_id_",
        "description": "(Schema options: { exclude: [ 'id' ] })",
        "properties": {
          "deleted": {
            "type": "boolean"
          },
          "createdOn": {
            "type": "string",
            "format": "date-time"
          },
          "modifiedOn": {
            "type": "string",
            "format": "date-time"
          },
          "createdBy": {
            "type": "string"
          },
          "modifiedBy": {
            "type": "string"
          },
          "email": {
            "type": "string"
          },
          "firstName": {
            "type": "string"
          },
          "lastName": {
            "type": "string"
          },
          "lastLogin": {
            "type": "string",
            "format": "date-time"
          },
          "username": {
            "type": "string"
          },
          "password": {
            "type": "string"
          }
        },
        "required": [
          "email",
          "firstName",
          "lastName",
          "username"
        ],
        "additionalProperties": true
      },
      "UserPartial": {
        "title": "UserPartial",
        "description": "(Schema options: { partial: true })",
        "properties": {
          "deleted": {
            "type": "boolean"
          },
          "createdOn": {
            "type": "string",
            "format": "date-time"
          },
          "modifiedOn": {
            "type": "string",
            "format": "date-time"
          },
          "createdBy": {
            "type": "string"
          },
          "modifiedBy": {
            "type": "string"
          },
          "id": {
            "type": "string"
          },
          "email": {
            "type": "string"
          },
          "firstName": {
            "type": "string"
          },
          "lastName": {
            "type": "string"
          },
          "lastLogin": {
            "type": "string",
            "format": "date-time"
          },
          "username": {
            "type": "string"
          },
          "password": {
            "type": "string"
          }
        },
        "additionalProperties": true
      },
      "PGP": {
        "title": "PGP",
        "properties": {
          "fingerprint": {
            "type": "string"
          },
          "xpub": {
            "type": "string"
          }
        },
        "required": [
          "fingerprint",
          "xpub"
        ],
        "additionalProperties": true
      },
      "AuthTokenRequest": {
        "title": "AuthTokenRequest",
        "properties": {
          "code": {
            "type": "string"
          },
          "clientId": {
            "type": "string"
          },
          "username": {
            "type": "string"
          }
        },
        "required": [
          "code",
          "clientId",
          "username"
        ],
        "additionalProperties": false
      },
      "LoginRequest": {
        "title": "LoginRequest",
        "properties": {
          "client_id": {
            "type": "string"
          },
          "client_secret": {
            "type": "string"
          },
          "username": {
            "type": "string"
          },
          "password": {
            "type": "string"
          }
        },
        "required": [
          "client_id",
          "client_secret",
          "username",
          "password"
        ],
        "additionalProperties": false
      },
      "TokenResponse": {
        "title": "TokenResponse",
        "properties": {
          "accessToken": {
            "type": "string"
          },
          "refreshToken": {
            "type": "string"
          }
        },
        "required": [
          "accessToken",
          "refreshToken"
        ],
        "additionalProperties": false
      },
      "AuthRefreshTokenRequest": {
        "title": "AuthRefreshTokenRequest",
        "properties": {
          "refreshToken": {
            "type": "string"
          }
        },
        "required": [
          "refreshToken"
        ],
        "additionalProperties": false
      }
    }
  },
  "servers": [
    {
      "url": "http://localhost:3000"
    }
  ]
}